ficc/__main__.py
ficc/constants.py
ficc/objects.py
ficc-0.1.0.dist-info/LICENSE
ficc-0.1.0.dist-info/METADATA
ficc-0.1.0.dist-info/WHEEL
ficc-0.1.0.dist-info/entry_points.txt
ficc-0.1.0.dist-info/RECORD
