Metadata-Version: 2.1
Name: ficc
Version: 0.1.0
Summary: Generates factorio blueprints for inserter clocks.
Home-page: https://pypi.org/project/ficc
License: MIT
Author: Ryan Delaney
Author-email: ryan.patrick.delaney+git@protonmail.com
Requires-Python: >=3.10,<4.0
Classifier: License :: OSI Approved :: MIT License
Classifier: Programming Language :: Python :: 3
Classifier: Programming Language :: Python :: 3.10
Classifier: Programming Language :: Python :: 3.11
Requires-Dist: factorio-draftsman (>=1.0.2,<2.0.0)
Project-URL: Repository, https://github.com/rpdelaney/factorio-inserter-clock-creator
